ace_components
