Metadata-Version: 1.0
Name: ace-components
Version: 0.0.2
Summary: Ace editor component suite
Home-page: UNKNOWN
Author: brymck
Author-email: UNKNOWN
License: MIT
Platform: UNKNOWN
